Metadata-Version: 1.1
Name: discgen
Version: 0.2.0
Summary: Discriminative Regularization for Generative Models
Home-page: https://github.com/dribnet/discgen
Author: Tom White
Author-email: tom@sixdozen.com
License: MIT
Download-URL: https://github.com/dribnet/discgen/archive/0.2.0.tar.gz
Platform: UNKNOWN
